README.md
setup.cfg
setup.py
genetic_algorithm/FloatGene.py
genetic_algorithm/GeneInterface.py
genetic_algorithm/Generation.py
genetic_algorithm/GeneticAlgorithm.py
genetic_algorithm/Individual.py
genetic_algorithm/IntGene.py
genetic_algorithm/ObjectGene.py
genetic_algorithm/__init__.py
genetic_algorithm.egg-info/PKG-INFO
genetic_algorithm.egg-info/SOURCES.txt
genetic_algorithm.egg-info/dependency_links.txt
genetic_algorithm.egg-info/requires.txt
genetic_algorithm.egg-info/top_level.txt