Metadata-Version: 2.1
Name: genetic-algorithm
Version: 1.0.0
Summary: A python package implementing the genetic algorithm
Home-page: https://github.com/YingxuH/genetic_algorithm
Author: He Yingxu
Author-email: yingxu.he1998@gmail.com
License: MIT
Download-URL: https://github.com/YingxuH/genetic_algorithm/archive/1.0.0.tar.gz
Keywords: genetic algorithm,machine learning,optimization
Platform: UNKNOWN
Classifier: Development Status :: 4 - Beta
Classifier: Intended Audience :: Developers
Classifier: Topic :: Software Development :: Build Tools
Classifier: License :: OSI Approved :: MIT License
Classifier: Programming Language :: Python :: 3
Classifier: Programming Language :: Python :: 3.4
Classifier: Programming Language :: Python :: 3.5
Classifier: Programming Language :: Python :: 3.6
Classifier: Programming Language :: Python :: 3.7
